fate_crypto_ops-0.3.0.dist-info/METADATA
fate_crypto_ops-0.3.0.dist-info/WHEEL
fate_crypto/psi/__init__.pyi
fate_crypto/psi/__init__.py
fate_crypto/hash/__init__.pyi
fate_crypto/hash/__init__.py
fate_crypto/__init__.py
fate_crypto/fate_crypto.cpython-310-i386-linux-gnu.so
fate_crypto_ops-0.3.0.dist-info/RECORD
